hermes/__init__.py
hermes/tmsi/__init__.py
hermes/tmsi/producer.py
hermes/tmsi/stream.py
hermes/tmsi/sdk/__init__.py
hermes/tmsi/sdk/tmsi_sdk.py
hermes/tmsi/sdk/device/__init__.py
hermes/tmsi/sdk/device/tmsi_channel.py
hermes/tmsi/sdk/device/tmsi_device.py
hermes/tmsi/sdk/device/tmsi_device_enums.py
hermes/tmsi/sdk/device/tmsi_dongle.py
hermes/tmsi/sdk/device/tmsi_event_reader.py
hermes/tmsi/sdk/device/tmsi_impedance_channel.py
hermes/tmsi/sdk/device/tmsi_measurement.py
hermes/tmsi/sdk/device/tmsi_thread.py
hermes/tmsi/sdk/device/devices/__init__.py
hermes/tmsi/sdk/device/devices/apex/__init__.py
hermes/tmsi/sdk/device/devices/apex/apex_API.py
hermes/tmsi/sdk/device/devices/apex/apex_API_enums.py
hermes/tmsi/sdk/device/devices/apex/apex_API_lookup_table.py
hermes/tmsi/sdk/device/devices/apex/apex_API_structures.py
hermes/tmsi/sdk/device/devices/apex/apex_device.py
hermes/tmsi/sdk/device/devices/apex/apex_dongle.py
hermes/tmsi/sdk/device/devices/apex/apex_event_reader.py
hermes/tmsi/sdk/device/devices/apex/apex_structures/__init__.py
hermes/tmsi/sdk/device/devices/apex/apex_structures/apex_channel.py
hermes/tmsi/sdk/device/devices/apex/apex_structures/apex_config.py
hermes/tmsi/sdk/device/devices/apex/apex_structures/apex_const.py
hermes/tmsi/sdk/device/devices/apex/apex_structures/apex_impedance_channel.py
hermes/tmsi/sdk/device/devices/apex/apex_structures/apex_info.py
hermes/tmsi/sdk/device/devices/apex/apex_structures/dongle_info.py
hermes/tmsi/sdk/device/devices/apex/measurements/__init__.py
hermes/tmsi/sdk/device/devices/apex/measurements/download_measurement.py
hermes/tmsi/sdk/device/devices/apex/measurements/impedance_measurement.py
hermes/tmsi/sdk/device/devices/apex/measurements/signal_measurement.py
hermes/tmsi/sdk/device/devices/saga/__init__.py
hermes/tmsi/sdk/device/devices/saga/saga_API.py
hermes/tmsi/sdk/device/devices/saga/saga_API_enums.py
hermes/tmsi/sdk/device/devices/saga/saga_API_lookup_table.py
pysio_hermes_tmsi-0.0.1.dist-info/licenses/LICENSE
pysio_hermes_tmsi-0.0.1.dist-info/METADATA
pysio_hermes_tmsi-0.0.1.dist-info/WHEEL
pysio_hermes_tmsi-0.0.1.dist-info/top_level.txt
pysio_hermes_tmsi-0.0.1.dist-info/RECORD
